Metadata-Version: 2.1
Name: latindictionary-io
Version: 0.0.1
Summary: latindictionary.io API
Home-page: https://www.latindictionary.io/api/docs
Author: latindictionary.io
Author-email: support@latindictionary.io
License: Apache-2.0
Keywords: latin,dictionary,latin dictionary,latindictionary.io,latin api
Platform: UNKNOWN
